<?xml version="1.0" encoding="UTF-8"?>
<services xmlns:xsi="http://www.w3.org/2001/XMLSchema-instance"
        xsi:noNamespaceSchemaLocation="http://moqui.org/xsd/service-definition-3.xsd">

    <service verb="login" noun="Session" type="script" allow-remote="true" authenticate="anonymous-all"
            location="component://darpan/src/main/groovy/darpan/facade/auth/loginSession.groovy">
        <description>Create an authenticated session from username/password and return the explicit Moqui login-key token darpan-ui sends on later requests.</description>
        <in-parameters>
            <parameter name="username" required="true">
                <description>Account username used for pilot login.</description>
            </parameter>
            <parameter name="password" required="true">
                <description>Account password used for pilot login.</description>
            </parameter>
        </in-parameters>
        <out-parameters>
            <parameter name="ok" type="Boolean">
                <description>True when the login attempt completed without facade errors.</description>
            </parameter>
            <parameter name="messages">
                <description>Informational messages emitted during login handling.</description>
                <parameter name="message"/>
            </parameter>
            <parameter name="errors">
                <description>Validation or authentication errors for the login attempt.</description>
                <parameter name="error"/>
            </parameter>
            <parameter name="authenticated" type="Boolean">
                <description>True when the session is authenticated after the login attempt.</description>
            </parameter>
            <parameter name="authToken" type="String">
                <description>Explicit login-key token that darpan-ui sends on later requests through the `login_key` header.</description>
            </parameter>
            <parameter name="authTokenType" type="String">
                <description>Token scheme identifier. Current value: `LOGIN_KEY`.</description>
            </parameter>
            <parameter name="authTokenHeaderName" type="String">
                <description>Request header name darpan-ui must send for stateless auth. Current value: `login_key`.</description>
            </parameter>
            <parameter name="authTokenExpiresInSeconds" type="Integer">
                <description>Approximate token lifetime in seconds, derived from the Moqui login-key expiry.</description>
            </parameter>
            <parameter name="sessionInfo">
                <description>Authenticated session metadata returned to darpan-ui.</description>
                <parameter name="userId" type="String"/>
                <parameter name="username" type="String"/>
                <parameter name="locale" type="String"/>
                <parameter name="timeZone" type="String"/>
                <parameter name="scopeType" type="String"/>
                <parameter name="customerScopeId" type="String"/>
                <parameter name="isSuperAdmin" type="Boolean"/>
            </parameter>
        </out-parameters>
    </service>

    <service verb="get" noun="SessionInfo" allow-remote="true" authenticate="anonymous-all">
        <description>Return session metadata for darpan-ui route guards. Moqui resolves the request user from the explicit `login_key` header when present.</description>
        <out-parameters>
            <parameter name="ok" type="Boolean">
                <description>True when the session info lookup completed without facade errors.</description>
            </parameter>
            <parameter name="messages">
                <description>Informational messages emitted during session-info lookup.</description>
                <parameter name="message"/>
            </parameter>
            <parameter name="errors">
                <description>Errors returned while resolving session state.</description>
                <parameter name="error"/>
            </parameter>
            <parameter name="authenticated" type="Boolean">
                <description>True when the current request resolves to an authenticated session.</description>
            </parameter>
            <parameter name="sessionInfo">
                <description>Authenticated session metadata returned to darpan-ui.</description>
                <parameter name="userId" type="String"/>
                <parameter name="username" type="String"/>
                <parameter name="locale" type="String"/>
                <parameter name="timeZone" type="String"/>
                <parameter name="scopeType" type="String"/>
                <parameter name="customerScopeId" type="String"/>
                <parameter name="isSuperAdmin" type="Boolean"/>
            </parameter>
        </out-parameters>
        <actions>
            <set field="authenticated" from="darpan.facade.common.FacadeSupport.normalize(ec.user.userId) != null"/>
            <if condition="authenticated">
                <set field="sessionInfo" from="darpan.facade.common.PilotAccessSupport.buildSessionInfo(ec)"/>
            </if>
            <set field="ok" from="!ec.message.hasError()"/>
            <set field="messages" from="darpan.facade.common.FacadeSupport.getMessages(ec)"/>
            <set field="errors" from="darpan.facade.common.FacadeSupport.getErrors(ec)"/>
        </actions>
    </service>

    <service verb="logout" noun="Session" type="script" allow-remote="true" authenticate="anonymous-all"
            location="component://darpan/src/main/groovy/darpan/facade/auth/logoutSession.groovy">
        <description>Revoke the explicit login-key token from the current request and terminate any active authenticated session.</description>
        <out-parameters>
            <parameter name="ok" type="Boolean">
                <description>True when logout cleanup completed without facade errors.</description>
            </parameter>
            <parameter name="messages">
                <description>Informational messages emitted during logout handling.</description>
                <parameter name="message"/>
            </parameter>
            <parameter name="errors">
                <description>Errors returned while clearing session state.</description>
                <parameter name="error"/>
            </parameter>
            <parameter name="authenticated" type="Boolean">
                <description>Always false after logout cleanup finishes.</description>
            </parameter>
            <parameter name="authTokenRevoked" type="Boolean">
                <description>True when logout removed the matching `UserLoginKey` record for the supplied auth token.</description>
            </parameter>
        </out-parameters>
    </service>
</services>
